MANIFEST.in
README.md
setup.cfg
setup.py
versioneer.py
tag/__init__.py
tag/__main__.py
tag/_version.py
tag/bae.py
tag/comment.py
tag/directive.py
tag/feature.py
tag/index.py
tag/locus.py
tag/range.py
tag/reader.py
tag/score.py
tag/select.py
tag/sequence.py
tag/transcript.py
tag/writer.py
tag.egg-info/PKG-INFO
tag.egg-info/SOURCES.txt
tag.egg-info/dependency_links.txt
tag.egg-info/entry_points.txt
tag.egg-info/requires.txt
tag.egg-info/top_level.txt
tag.egg-info/zip-safe
tag/cli/__init__.py
tag/cli/bae.py
tag/cli/bcollapse.py
tag/cli/gff3.py
tag/cli/locuspocus.py
tag/cli/merge.py
tag/cli/occ.py
tag/cli/pmrna.py
tag/cli/sum.py
tag/tests/__init__.py
tag/tests/test_bae.py
tag/tests/test_cli.py
tag/tests/test_comment.py
tag/tests/test_directive.py
tag/tests/test_feature.py
tag/tests/test_index.py
tag/tests/test_locus.py
tag/tests/test_range.py
tag/tests/test_reader.py
tag/tests/test_score.py
tag/tests/test_select.py
tag/tests/test_sequence.py
tag/tests/test_transcript.py
tag/tests/test_utils.py
tag/tests/test_writer.py
tag/tests/data/GCF_001639295.1_ASM163929v1_genomic.gff.gz
tag/tests/data/Ye.callgenes.gff3.gz
tag/tests/data/Ye.callgenes.min.gff3.gz
tag/tests/data/Ye.glimmer.gff3.gz
tag/tests/data/Ye.glimmer.min.gff3.gz
tag/tests/data/Ye.loci.gff3
tag/tests/data/Ye.loci.tsv.gz
tag/tests/data/Ye.prodigal.gff3.gz
tag/tests/data/Ye.prodigal.min.gff3.gz
tag/tests/data/Ye.region01.gff3
tag/tests/data/Ye.region02.bae.gff3
tag/tests/data/Ye.region02.gff3
tag/tests/data/amel-cdna-multi-out.gff3
tag/tests/data/amel-cdna-multi.gff3
tag/tests/data/bogus-aligns.gff3
tag/tests/data/bogus-genes.gff3
tag/tests/data/boring-exons.gff3
tag/tests/data/boring-genes.gff3
tag/tests/data/bork-out.gff3
tag/tests/data/bork.gff3
tag/tests/data/cds-occ-orig.gff3
tag/tests/data/cds-occ.gff3
tag/tests/data/eden-mismatch.gff3
tag/tests/data/eden-mod.gff3
tag/tests/data/eden.gff3
tag/tests/data/ex-red-1.gff3
tag/tests/data/ex-red-2.gff3
tag/tests/data/ex-red-3.gff3
tag/tests/data/ex-red-merged.gff3
tag/tests/data/grape-cpgat-no-sep.gff3
tag/tests/data/grape-cpgat-seqreg-after.gff3.gz
tag/tests/data/grape-cpgat-shuffled.gff3
tag/tests/data/grape-cpgat-sorted.gff3
