Metadata-Version: 1.1
Name: tag
Version: 0.4
Summary: Genome annotation data analysis and management implemented in pure Python
Home-page: http://tag.readthedocs.io
Author: Daniel Standage
Author-email: daniel.standage@gmail.com
License: BSD-3
Platform: UNKNOWN
Classifier: Development Status :: 4 - Beta
Classifier: Environment :: Console
Classifier: License :: OSI Approved :: BSD License
Classifier: Programming Language :: Python :: 3.5
Classifier: Programming Language :: Python :: 3.6
Classifier: Programming Language :: Python :: 3.7
Classifier: Programming Language :: Python :: 3.8
Classifier: Topic :: Scientific/Engineering :: Bio-Informatics
